subdata/__init__.py
subdata/download.py
subdata/main.py
subdata/process.py
subdata/update.py
subdata/utils.py
subdata/resources/__init__.py
subdata/resources/__init__.py:Zone.Identifier
subdata/resources/__init__.py:Zone.Identifier:Zone.Identifier
subdata/resources/download_dict.json
subdata/resources/download_dict.json:Zone.Identifier
subdata/resources/download_dict.json:Zone.Identifier:Zone.Identifier
subdata/resources/instruction_dict.json
subdata/resources/instruction_dict.json:Zone.Identifier
subdata/resources/instruction_dict.json:Zone.Identifier:Zone.Identifier
subdata/resources/mapping_original.json
subdata/resources/mapping_original.json:Zone.Identifier
subdata/resources/overview_original.json
subdata/resources/overview_original.json:Zone.Identifier
subdata/resources/process_dict.json
subdata/resources/process_dict.json:Zone.Identifier
subdata/resources/process_dict.json:Zone.Identifier:Zone.Identifier
subdata/resources/taxonomy_original.json
subdata/resources/taxonomy_original.json:Zone.Identifier
subdata-1.0.1.dist-info/licenses/LICENSE.txt
subdata-1.0.1.dist-info/METADATA
subdata-1.0.1.dist-info/WHEEL
subdata-1.0.1.dist-info/top_level.txt
subdata-1.0.1.dist-info/RECORD
