Metadata-Version: 2.4
Name: subdata
Version: 1.0.1
Summary: A Python library for automatically creating targeted hate speech datasets.
Author-email: Subdata <subdatalibrary@gmail.com>
License: GNU
Project-URL: Homepage, https://github.com/subdata-library/subdata
Requires-Python: >=3.11
License-File: LICENSE.txt
Requires-Dist: pandas
Requires-Dist: numpy
Requires-Dist: huggingface_hub
Requires-Dist: pyarrow
Dynamic: license-file
